{
  "date": "2025-06-04",
  "total_calls": 9,
  "successful_calls": data/2025/06/04/metadata_060246.txt:1
data/2025/06/04/metadata_062343.txt:1
data/2025/06/04/metadata_064905.txt:1
data/2025/06/04/metadata_065119.txt:1
data/2025/06/04/metadata_071419.txt:1
data/2025/06/04/metadata_072300.txt:1
data/2025/06/04/metadata_073134.txt:1
data/2025/06/04/metadata_074150.txt:1
data/2025/06/04/metadata_074813.txt:1,
  "failed_calls": data/2025/06/04/metadata_060246.txt:0
data/2025/06/04/metadata_062343.txt:0
data/2025/06/04/metadata_064905.txt:0
data/2025/06/04/metadata_065119.txt:0
data/2025/06/04/metadata_071419.txt:0
data/2025/06/04/metadata_072300.txt:0
data/2025/06/04/metadata_073134.txt:0
data/2025/06/04/metadata_074150.txt:0
data/2025/06/04/metadata_074813.txt:0
0,
  "success_rate_percent": ,
  "last_updated": "2025-06-04 07:48:16 UTC",
  "last_trigger": "schedule"
}
