{
  "date": "2025-06-06",
  "total_calls": 10,
  "successful_calls": data/2025/06/06/metadata_010810.txt:1
data/2025/06/06/metadata_020706.txt:1
data/2025/06/06/metadata_025242.txt:1
data/2025/06/06/metadata_032106.txt:1
data/2025/06/06/metadata_034248.txt:1
data/2025/06/06/metadata_035900.txt:1
data/2025/06/06/metadata_040314.txt:1
data/2025/06/06/metadata_043537.txt:1
data/2025/06/06/metadata_044048.txt:1
data/2025/06/06/metadata_045331.txt:1,
  "failed_calls": data/2025/06/06/metadata_010810.txt:0
data/2025/06/06/metadata_020706.txt:0
data/2025/06/06/metadata_025242.txt:0
data/2025/06/06/metadata_032106.txt:0
data/2025/06/06/metadata_034248.txt:0
data/2025/06/06/metadata_035900.txt:0
data/2025/06/06/metadata_040314.txt:0
data/2025/06/06/metadata_043537.txt:0
data/2025/06/06/metadata_044048.txt:0
data/2025/06/06/metadata_045331.txt:0
0,
  "success_rate_percent": ,
  "last_updated": "2025-06-06 04:53:34 UTC",
  "last_trigger": "schedule"
}
